whats77/__init__.py
whats77/whats_main.py
whats77-0.1.3.dist-info/METADATA
whats77-0.1.3.dist-info/WHEEL
whats77-0.1.3.dist-info/top_level.txt
whats77-0.1.3.dist-info/RECORD
