Metadata-Version: 2.4
Name: whats77
Version: 0.1.3
Summary: Facilitador para uso da API WhatsApp (ZAPI)
Home-page: https://github.com/77-Indicadores/modulo_whatsapp
Author: Vinicius Moreira
Author-email: vinicius@77indicadores.com.br
Classifier: Programming Language :: Python :: 3
Classifier: License :: OSI Approved :: MIT License
Classifier: Operating System :: OS Independent
Requires-Python: >=3.8
Requires-Dist: requests>=2.0.0
Requires-Dist: python-dotenv>=0.21.0
Dynamic: author
Dynamic: author-email
Dynamic: classifier
Dynamic: description
Dynamic: description-content-type
Dynamic: home-page
Dynamic: requires-dist
Dynamic: requires-python
Dynamic: summary
